flight_mech/__init__.py
flight_mech/_common.py
flight_mech/aerodynamics.py
flight_mech/airfoil.py
flight_mech/atmosphere.py
flight_mech/fuel.py
flight_mech/motor.py
flight_mech/plane.py
flight_mech/turbine.py
flight_mech/wing.py
flight_mech/airfoil_database/ag08.txt
flight_mech/airfoil_database/e591.txt
flight_mech/airfoil_database/fx62k153.txt
flight_mech/airfoil_database/n11h9.txt
flight_mech/airfoil_database/n2415.txt
flight_mech/airfoil_database/naca2412.txt
flight_mech/airfoil_database/naca4412.txt
flight_mech/airfoil_database/naca65210.txt
flight_mech/motor_database/electron_100.json
flight_mech/motor_database/electron_12.5.json
flight_mech/motor_database/electron_25.json
flight_mech/motor_database/electron_60.json
flight_mech/motor_database/emrax_188_high_voltage.json
flight_mech/plane_database/cessna_172.json
flight_mech/plane_database/cessna_citation_III.json
flight_mech/plane_database/cessna_citation_mustang.json
flight_mech-1.0.8.dist-info/METADATA
flight_mech-1.0.8.dist-info/WHEEL
flight_mech-1.0.8.dist-info/licenses/LICENSE
flight_mech-1.0.8.dist-info/RECORD
