Metadata-Version: 2.4
Name: flight-mech
Version: 1.0.8
Summary: A package to compute the characteristics of an airplane using simple flight mechanics equations.
Project-URL: Homepage, https://github.com/PaulCreusy/flight-mech
Project-URL: Issues, https://github.com/PaulCreusy/flight-mech/issues
Project-URL: Documentation, https://flight-mech.creusy.fr
Author-email: PaulCreusy <paul.creusy@gmail.com>
License-File: LICENSE
Keywords: airfoil,airfoil-analysis,airplane,flight,flight mechanics,mechanics,plane,turbojet,wing
Classifier: License :: OSI Approved :: MIT License
Classifier: Operating System :: OS Independent
Classifier: Programming Language :: Python :: 3
Requires-Python: >=3.10
Requires-Dist: bs4
Requires-Dist: matplotlib
Requires-Dist: numpy>=2.0.0
Requires-Dist: pandas
Requires-Dist: scipy
Requires-Dist: tqdm
